validata_api/README.md
validata_api/__init__.py
validata_api/api/__init__.py
validata_api/api/config.py
validata_api/api/json_errors.py
validata_api/api/route_handlers.py
validata_core/ERRORS.md
validata_core/README.md
validata_core/__init__.py
validata_core/custom_checks/README.md
validata_core/custom_checks/__init__.py
validata_core/custom_checks/cohesive_columns_value.py
validata_core/custom_checks/compare_columns_value.py
validata_core/custom_checks/french_gps_coordinates.py
validata_core/custom_checks/nomenclature_actes_value.py
validata_core/custom_checks/one_of_required.py
validata_core/custom_checks/opening_hours_value.py
validata_core/custom_checks/phone_number_value.py
validata_core/custom_checks/sum_columns_value.py
validata_core/custom_checks/year_interval_value.py
validata_core/domain/__init__.py
validata_core/domain/check.py
validata_core/domain/cli.py
validata_core/domain/dict_parser.py
validata_core/domain/fr_locale.py
validata_core/domain/schema_features.py
validata_core/domain/spi.py
validata_core/domain/structure_warnings.py
validata_core/domain/table_reader.py
validata_core/domain/table_resource.py
validata_core/domain/types/__init__.py
validata_core/domain/types/check_descriptor.py
validata_core/domain/types/error.py
validata_core/domain/types/error_tags.py
validata_core/domain/types/error_types.py
validata_core/domain/types/field.py
validata_core/domain/types/json.py
validata_core/domain/types/locale.py
validata_core/domain/types/metadata.py
validata_core/domain/types/options.py
validata_core/domain/types/report.py
validata_core/domain/types/resource.py
validata_core/domain/types/schema.py
validata_core/domain/types/source.py
validata_core/domain/types/table_region.py
validata_core/domain/types/typed_exception.py
validata_core/domain/utils.py
validata_core/domain/validation_features.py
validata_core/domain/validator.py
validata_core/domain/warning_messages.py
validata_core/infrastructure/descriptor_readers.py
validata_table-0.12.5.dist-info/LICENSE
validata_table-0.12.5.dist-info/METADATA
validata_table-0.12.5.dist-info/WHEEL
validata_table-0.12.5.dist-info/entry_points.txt
validata_table-0.12.5.dist-info/RECORD
